{
  "chapters": {
    "1": {
      "pendingViews": 4,
      "lastIncrement": "2026-01-22T15:58:07.425Z",
      "lastUpdate": "2026-01-18T00:12:21+07:00"
    },
    "3": {
      "pendingViews": 2,
      "lastIncrement": "2026-01-22T16:03:28.800Z",
      "lastUpdate": "2026-01-16T00:27:00+07:00"
    },
    "4": {
      "pendingViews": 0,
      "lastIncrement": "2026-01-15T08:54:33.705Z",
      "lastUpdate": "2026-01-16T00:27:00+07:00"
    },
    "5": {
      "pendingViews": 0,
      "lastIncrement": "2026-01-15T08:55:44.977Z",
      "lastUpdate": "2026-01-16T00:27:00+07:00"
    },
    "6": {
      "pendingViews": 0,
      "lastIncrement": "2026-01-15T08:56:45.402Z",
      "lastUpdate": "2026-01-16T00:27:00+07:00"
    },
    "7": {
      "pendingViews": 2,
      "lastIncrement": "2026-01-21T21:26:48.900Z",
      "lastUpdate": "2026-01-19T00:12:21+07:00"
    },
    "8": {
      "pendingViews": 3,
      "lastIncrement": "2026-01-21T21:26:18.511Z",
      "lastUpdate": "2026-01-16T00:27:00+07:00"
    },
    "9": {
      "pendingViews": 6,
      "lastIncrement": "2026-01-21T21:26:01.253Z",
      "lastUpdate": "2026-01-20T00:18:45+07:00"
    },
    "10": {
      "pendingViews": 10,
      "lastIncrement": "2026-01-22T11:44:54.877Z",
      "lastUpdate": "2026-01-20T00:18:45+07:00"
    },
    "2.1": {
      "pendingViews": 2,
      "lastIncrement": "2026-01-22T16:00:49.630Z",
      "lastUpdate": "2026-01-16T00:27:00+07:00"
    },
    "2.2": {
      "pendingViews": 2,
      "lastIncrement": "2026-01-22T16:01:58.102Z",
      "lastUpdate": "2026-01-16T00:27:00+07:00"
    }
  },
  "lastUpdated": "2026-01-20T00:18:44+07:00"
}